{
  "name": "PyAOT Tokenizer",
  "version": "1.0.0",
  "description": "Fast BPE tokenizer in Zig",
  "performance": {
    "encoding": "2.489s",
    "vs_rs_bpe": "1.55x faster",
    "correctness": true
  },
  "features": ["BPE encoding", "Training", "WASM support"],
  "benchmarks": [
    {"library": "PyAOT", "time": 2.489},
    {"library": "rs-bpe", "time": 3.866},
    {"library": "tiktoken", "time": 9.311}
  ],
  "metadata": {
    "author": "PyAOT Team",
    "license": "MIT",
    "repo": "https://github.com/teamchong/pyaot"
  }
}
